benchmarks/__init__.py
benchmarks/arg_parser.py
benchmarks/benchmark_result.py
benchmarks/benchmark_result_list.py
benchmarks/benchmark_run.py
benchmarks/benchmark_run_summary.py
benchmarks/benchmark_runner.py
benchmarks/context_benchmark.py
benchmarks/edit_rubric_benchmark.py
benchmarks/exercism_practice.py
benchmarks/plot_generator.py
benchmarks/run_sample.py
benchmarks/swe_bench_runner.py
benchmarks/exercise_runners/__init__.py
benchmarks/exercise_runners/abstract_exercise_runner.py
benchmarks/exercise_runners/clojure_exercise_runner.py
benchmarks/exercise_runners/exercise_runner_factory.py
benchmarks/exercise_runners/javascript_exercise_runner.py
benchmarks/exercise_runners/python_exercise_runner.py
benchmarks/resources/templates/benchmark.jinja
benchmarks/resources/templates/benchmark_list.jinja
benchmarks/resources/templates/css/benchmark.css
benchmarks/resources/templates/css/benchmark_list.css
mentat/VERSION
mentat/__init__.py
mentat/__main__.py
mentat/agent_handler.py
mentat/app_conf.py
mentat/auto_completer.py
mentat/broadcast.py
mentat/code_context.py
mentat/code_edit_feedback.py
mentat/code_feature.py
mentat/code_file_manager.py
mentat/config.py
mentat/conversation.py
mentat/daemon.py
mentat/diff_context.py
mentat/edit_history.py
mentat/errors.py
mentat/git_handler.py
mentat/include_files.py
mentat/interval.py
mentat/llm_api_handler.py
mentat/logging_config.py
mentat/sentry.py
mentat/session.py
mentat/session_context.py
mentat/session_input.py
mentat/session_stream.py
mentat/splash_messages.py
mentat/transcripts.py
mentat/utils.py
mentat/version.py
mentat/command/__init__.py
mentat/command/command.py
mentat/command/commands/__init__.py
mentat/command/commands/agent.py
mentat/command/commands/amend.py
mentat/command/commands/clear.py
mentat/command/commands/commit.py
mentat/command/commands/config.py
mentat/command/commands/exclude.py
mentat/command/commands/help.py
mentat/command/commands/include.py
mentat/command/commands/load.py
mentat-1.0.19.dist-info/METADATA
mentat-1.0.19.dist-info/WHEEL
mentat-1.0.19.dist-info/entry_points.txt
mentat-1.0.19.dist-info/top_level.txt
mentat-1.0.19.dist-info/RECORD
